{"mainboard_uses":{"YxxD9":1,"EbwMa":1,"LGbo4":1,"Yed0R":1,"LGKwx":1,"LKmKo":1,"Ye13Q":1,"LDezW":1,"E1RMz":1,"EbJoX":1,"k9AK7":1,"EZymV":1,"Lzd6N":1,"kXrrZ":1,"EJV94":1,"YdDVX":1,"k7Arj":1,"Yn1WN":1,"E058J":1,"LG24x":1,"Yo0lA":1,"YjrN7":1,"YnvQ5":1,"L4gNP":1,"kqAb3":7,"EZyKV":1,"ky6zr":1,"LKw8m":1,"kAnJe":1,"Lzo5N":1,"k9vG6":1,"EW9zZ":1,"LwR84":1,"E1R1e":1,"Yn0Q3":1,"L3OlK":1,"EPr8p":1,"Yx4VV":1,"L4Xz6":1,"kXoZA":1,"EJNdM":1,"Yxmnn":1,"YNJqQ":1,"LzogN":1,"kqABy":1,"Lz6qX":1,"Yn1px":1,"kA5yA":1,"kpAaJ":1,"kAqNR":1,"YBBa8":1,"Ye1xR":1,"Yn0Gx":1,"E0rbv":1},"sideboard_uses":{"ky6qD":1,"EZdjN":1,"kXwKo":1,"YdV7a":1,"EbyoP":1,"YxQny":1,"YBJPW":1,"YojD2":1,"E12yv":1,"YoD6b":1,"kpvyw":1,"YMD2N":1,"EW9Pb":1,"E5plv":1,"Y2yl4":1},"pointed_uses":{"Yxmnn":1,"EJNdM":1,"EZyKV":1,"EW9zZ":1,"LKw8m":1,"Ye13Q":1},"non_pointed_uses":{"EbyoP":1,"EPr8p":1,"YBJPW":1,"LG24x":1,"YNJqQ":1,"Yo0lA":1,"ky6qD":1,"kXoZA":1,"YnvQ5":1,"ky6zr":1,"L4Xz6":1,"kpAaJ":1,"EZymV":1,"YBBa8":1,"EZdjN":1,"EbwMa":1,"L3OlK":1,"LGbo4":1,"E0rbv":1,"YdV7a":1,"k7Arj":1,"kAqNR":1,"LwR84":1,"E1RMz":1,"YoD6b":1,"YxQny":1,"kA5yA":1,"kpvyw":1,"Yn0Gx":1,"Yn1px":1,"YjrN7":1,"YxxD9":1,"E1R1e":1,"Ye1xR":1,"kAnJe":1,"kqAb3":1,"Lz6qX":1,"Lzo5N":1,"kXwKo":1,"L4gNP":1,"E12yv":1,"E058J":1,"LGKwx":1,"YdDVX":1,"k9vG6":1,"LzogN":1,"E5plv":1,"LKmKo":1,"EbJoX":1,"Yx4VV":1,"Yn1WN":1,"Yn0Q3":1,"kqABy":1,"Yed0R":1,"Lzd6N":1,"LDezW":1,"k9AK7":1,"EW9Pb":1,"EJV94":1,"Y2yl4":1,"kXrrZ":1,"YojD2":1,"YMD2N":1}}